[
  {
    "id": 1,
    "value": 155,
    "age": 20,
    "name": "Huber Ellis",
    "gender": "male",
    "email": "huberellis@bitrex.com",
    "totalTasks": 14,
    "completedTasks": 3,
    "address": "420 Cedar Street, Avalon, Oklahoma, 8058"
  },
  {
    "id": 2,
    "value": 204,
    "age": 37,
    "name": "Cruz Wolf",
    "gender": "male",
    "email": "cruzwolf@bitrex.com",
    "totalTasks": 11,
    "completedTasks": 8,
    "address": "458 Colonial Court, Klagetoh, Colorado, 5290"
  },
  {
    "id": 3,
    "value": 260,
    "age": 22,
    "name": "Hardy Vinson",
    "gender": "male",
    "email": "hardyvinson@bitrex.com",
    "totalTasks": 10,
    "completedTasks": 7,
    "address": "689 Ainslie Street, Calvary, Delaware, 4472"
  },
  {
    "id": 4,
    "value": 286,
    "age": 26,
    "name": "Bray Cole",
    "gender": "male",
    "email": "braycole@bitrex.com",
    "totalTasks": 13,
    "completedTasks": 4,
    "address": "265 Pooles Lane, Wyano, Arkansas, 3664"
  },
  {
    "id": 5,
    "value": 270,
    "age": 40,
    "name": "Shannon Henderson",
    "gender": "male",
    "email": "shannonhenderson@bitrex.com",
    "totalTasks": 13,
    "completedTasks": 4,
    "address": "738 Hendrickson Place, Devon, Virginia, 1995"
  },
  {
    "id": 6,
    "value": 138,
    "age": 31,
    "name": "Hickman Lowe",
    "gender": "male",
    "email": "hickmanlowe@bitrex.com",
    "totalTasks": 13,
    "completedTasks": 7,
    "address": "842 Woodhull Street, Elizaville, American Samoa, 8501"
  },
  {
    "id": 7,
    "value": 108,
    "age": 30,
    "name": "Juarez Dunn",
    "gender": "male",
    "email": "juarezdunn@bitrex.com",
    "totalTasks": 15,
    "completedTasks": 7,
    "address": "488 Florence Avenue, Marienthal, Missouri, 870"
  },
  {
    "id": 8,
    "value": 103,
    "age": 34,
    "name": "Corina Valentine",
    "gender": "female",
    "email": "corinavalentine@bitrex.com",
    "totalTasks": 11,
    "completedTasks": 8,
    "address": "480 Cortelyou Road, Fontanelle, New Hampshire, 681"
  },
  {
    "id": 9,
    "value": 213,
    "age": 20,
    "name": "Margaret Medina",
    "gender": "female",
    "email": "margaretmedina@bitrex.com",
    "totalTasks": 11,
    "completedTasks": 9,
    "address": "421 Sunnyside Court, Comptche, Hawaii, 5860"
  },
  {
    "id": 10,
    "value": 185,
    "age": 39,
    "name": "Elliott Willis",
    "gender": "male",
    "email": "elliottwillis@bitrex.com",
    "totalTasks": 15,
    "completedTasks": 9,
    "address": "110 Woodbine Street, Dundee, Minnesota, 9559"
  },
  {
    "id": 11,
    "value": 149,
    "age": 31,
    "name": "Jackie Reilly",
    "gender": "female",
    "email": "jackiereilly@bitrex.com",
    "totalTasks": 11,
    "completedTasks": 9,
    "address": "345 Putnam Avenue, Manila, Nebraska, 9206"
  },
  {
    "id": 12,
    "value": 234,
    "age": 27,
    "name": "Robert Albert",
    "gender": "female",
    "email": "robertalbert@bitrex.com",
    "totalTasks": 11,
    "completedTasks": 4,
    "address": "363 Bartlett Place, Sheatown, Guam, 8165"
  },
  {
    "id": 13,
    "value": 227,
    "age": 26,
    "name": "Kathie Mayo",
    "gender": "female",
    "email": "kathiemayo@bitrex.com",
    "totalTasks": 10,
    "completedTasks": 9,
    "address": "905 Lawrence Avenue, Coultervillle, Washington, 5198"
  },
  {
    "id": 14,
    "value": 229,
    "age": 35,
    "name": "Mitchell Ross",
    "gender": "male",
    "email": "mitchellross@bitrex.com",
    "totalTasks": 11,
    "completedTasks": 9,
    "address": "688 Glendale Court, Cuylerville, Puerto Rico, 1019"
  },
  {
    "id": 15,
    "value": 124,
    "age": 22,
    "name": "Hughes Christensen",
    "gender": "male",
    "email": "hugheschristensen@bitrex.com",
    "totalTasks": 11,
    "completedTasks": 9,
    "address": "680 Thames Street, Malott, Mississippi, 8824"
  }
]